vise_logger/__init__.py
vise_logger/conversation.json
vise_logger/conversation10.json
vise_logger/conversation11.json
vise_logger/conversation2.json
vise_logger/conversation3.json
vise_logger/conversation4.json
vise_logger/conversation5.json
vise_logger/conversation6.json
vise_logger/conversation7.json
vise_logger/conversation8.json
vise_logger/conversation9.json
vise_logger/conversation_alternate.json
vise_logger/conversation_part.json
vise_logger/extract_from_sqlite.py
vise_logger/iban.txt
vise_logger/iban_sorted.txt
vise_logger/localizations.py
vise_logger/locations.json
vise_logger/main.py
vise_logger/main.py.temporaryDir
vise_logger/privacy.py
vise_logger/pseudonymization copy 2.py
vise_logger/search.py
vise_logger-0.1.3.dist-info/METADATA
vise_logger-0.1.3.dist-info/WHEEL
vise_logger-0.1.3.dist-info/entry_points.txt
vise_logger-0.1.3.dist-info/licenses/LICENSE.future
vise_logger-0.1.3.dist-info/RECORD
