Metadata-Version: 2.4
Name: vise-logger
Version: 0.1.3
Summary: MCP server for logging Vise Coding sessions.
Project-URL: Homepage, https://github.com/DavidFarago/vise-logger
Project-URL: Coud_Hosted_Logs, https://viselo.gr/
Project-URL: Source, https://github.com/DavidFarago/vise-logger
Project-URL: Issues, https://github.com/DavidFarago/vise-logger/issues
Project-URL: Changelog, https://github.com/DavidFarago/vise-logger/blob/main/CHANGELOG.md
Author-email: David Faragó <drdavidfarago@gmail.com>
License-File: LICENSE.future
Requires-Python: >=3.10
Requires-Dist: mcp
Requires-Dist: opentelemetry-api>=1.36.0
Requires-Dist: opentelemetry-exporter-otlp-proto-http>=1.36.0
Requires-Dist: opentelemetry-sdk>=1.36.0
Requires-Dist: platformdirs
Requires-Dist: requests
Provides-Extra: dev
Requires-Dist: mypy; extra == 'dev'
Requires-Dist: pytest; extra == 'dev'
Requires-Dist: ruff; extra == 'dev'
Requires-Dist: types-requests; extra == 'dev'
